filabres/__init__.py
filabres/check_args_compatibility.py
filabres/check_datadir.py
filabres/check_image_classification.py
filabres/check_image_corrections.py
filabres/check_image_ignore.py
filabres/check_list_filter.py
filabres/check_list_mode.py
filabres/check_tslash.py
filabres/classify_images.py
filabres/cmdexecute.py
filabres/delete_reduced.py
filabres/filabres.py
filabres/fileinfo.py
filabres/generate_setup.py
filabres/list_classified.py
filabres/list_originf.py
filabres/list_reduced.py
filabres/load_instrument_configuration.py
filabres/load_scamp_cat.py
filabres/load_setup.py
filabres/maskfromflat.py
filabres/matplotlib_qt.py
filabres/nights_to_be_reduced.py
filabres/overplot_ds9reg.py
filabres/pause_debugplot.py
filabres/plot_astrometry.py
filabres/progressbar.py
filabres/retrieve_calibration.py
filabres/retrieve_gaia.py
filabres/run_astrometry.py
filabres/run_calibration_step.py
filabres/run_reduction_step.py
filabres/show_df.py
filabres/signature.py
filabres/single_list_of_files.py
filabres/stats.py
filabres/statsumm.py
filabres/tologfile.py
filabres/version.py
filabres/visualization.py
filabres/ximshow.py
filabres/astromatic/__init__.py
filabres/astromatic/config.scamp
filabres/astromatic/config.sex
filabres/astromatic/default.param
filabres/instrument/__init__.py
filabres/instrument/configuration_cafos.yaml
filabres/instrument/configuration_lsss.yaml
filabres/tests/__init__.py
filabres/tests/test_1.py
filabres/tools/__init__.py
filabres/tools/rotate_flipstat.py
filabres-1.5.1.dist-info/LICENSE.txt
filabres-1.5.1.dist-info/METADATA
filabres-1.5.1.dist-info/WHEEL
filabres-1.5.1.dist-info/entry_points.txt
filabres-1.5.1.dist-info/top_level.txt
filabres-1.5.1.dist-info/RECORD
