Metadata-Version: 2.1
Name: filabres
Version: 1.5.1
Summary: Data Reduction Package for CAHA instruments
Author-email: Nicolás Cardiel <cardiel@ucm.es>
License: GPL-3.0-or-later
Project-URL: Homepage, https://github.com/nicocardiel/filabres
Project-URL: Repository, https://github.com/nicocardiel/filabres.git
Project-URL: Documentation, https://filabres.readthedocs.io/
Classifier: Programming Language :: Python :: 3.8
Classifier: Programming Language :: Python :: 3.9
Classifier: Programming Language :: Python :: 3.10
Classifier: Programming Language :: Python :: 3.11
Classifier: Programming Language :: Python :: 3.12
Classifier: Development Status :: 3 - Alpha
Classifier: Environment :: Console
Classifier: Intended Audience :: Science/Research
Classifier: License :: OSI Approved :: GNU General Public License (GPL)
Classifier: Operating System :: OS Independent
Classifier: Topic :: Scientific/Engineering :: Astronomy
Requires-Python: >=3.8
License-File: LICENSE.txt
Requires-Dist: astropy
Requires-Dist: astroquery
Requires-Dist: numpy
Requires-Dist: matplotlib
Requires-Dist: scipy
Requires-Dist: pandas
Requires-Dist: python-dateutil
Requires-Dist: PyYaml
Provides-Extra: docs
Requires-Dist: sphinx ; extra == 'docs'
Requires-Dist: sphinx-rtd-theme ; extra == 'docs'
Provides-Extra: test
Requires-Dist: pytest ; extra == 'test'
